refl1d/__init__.py
refl1d/__main__.py
refl1d/_version.py
refl1d/backends.py
refl1d/dist.py
refl1d/experiment.py
refl1d/main.py
refl1d/names.py
refl1d/profile.py
refl1d/uncertainty.py
refl1d/bumps_interface/__init__.py
refl1d/bumps_interface/fitplugin.py
refl1d/bumps_interface/migrations.py
refl1d/deprecated/__init__.py
refl1d/deprecated/freeform.py
refl1d/deprecated/magnetic.py
refl1d/lib/__init__.py
refl1d/lib/c/build_profile.cc
refl1d/lib/c/contract_profile.cc
refl1d/lib/c/convolve.cc
refl1d/lib/c/convolve_sampled.cc
refl1d/lib/c/erf.cc
refl1d/lib/c/magnetic.cc
refl1d/lib/c/magnetic_CD_tempered.cc
refl1d/lib/c/methods.cc
refl1d/lib/c/methods.h
refl1d/lib/c/rebin.h
refl1d/lib/c/rebin2D.h
refl1d/lib/c/rebin2D_test.cc
refl1d/lib/c/rebin_test.cc
refl1d/lib/c/reflcalc.h
refl1d/lib/c/reflectivity.cc
refl1d/lib/c/reflmodule.cc
refl1d/lib/numba/__init__.py
refl1d/lib/numba/build_profile.py
refl1d/lib/numba/clone_module.py
refl1d/lib/numba/contract_profile.py
refl1d/lib/numba/convolve.py
refl1d/lib/numba/convolve_sampled.py
refl1d/lib/numba/magnetic.py
refl1d/lib/numba/rebin.py
refl1d/lib/numba/reflectivity.py
refl1d/lib/python/__init__.py
refl1d/lib/python/build_profile.py
refl1d/lib/python/contract_profile.py
refl1d/lib/python/convolve.py
refl1d/lib/python/convolve_sampled.py
refl1d/lib/python/magnetic.py
refl1d/lib/python/rebin.py
refl1d/lib/python/reflectivity.py
refl1d/probe/__init__.py
refl1d/probe/abeles.py
refl1d/probe/fresnel.py
refl1d/probe/instrument.py
refl1d/probe/oversampling.py
refl1d/probe/probe.py
refl1d/probe/resolution.py
refl1d/probe/stitch.py
refl1d/probe/data_loaders/__init__.py
refl1d/probe/data_loaders/anstodata.py
refl1d/probe/data_loaders/load4.py
refl1d/probe/data_loaders/ncnrdata.py
refl1d/probe/data_loaders/rebin.py
refl1d/probe/data_loaders/snsdata.py
refl1d/probe/data_loaders/staj.py
refl1d/probe/data_loaders/stajconvert.py
refl1d/sample/__init__.py
refl1d/sample/cheby.py
refl1d/sample/flayer.py
refl1d/sample/layers.py
refl1d-1.0.0.dist-info/licenses/LICENSE.txt
refl1d-1.0.0.dist-info/METADATA
refl1d-1.0.0.dist-info/WHEEL
refl1d-1.0.0.dist-info/entry_points.txt
refl1d-1.0.0.dist-info/top_level.txt
refl1d-1.0.0.dist-info/RECORD
