Metadata-Version: 2.4
Name: refl1d
Version: 1.0.0
Summary: Neutron and X-ray reflectometry analysis
Author-email: Paul Kienzle <paul.kienzle@nist.gov>, Brian Maranville <brian.maranville@nist.gov>, Andrew Caruana <andrew.caruana@stfc.uk>, Mathieu Doucet <doucetm@ornl.gov>
License: Copyright 2006-2024 The Refl1D Contributors
Project-URL: documentation, https://refl1d.github.io
Project-URL: homepage, https://refl1d.github.io
Project-URL: repository, https://github.com/reflectometry/refl1d
Classifier: Development Status :: 4 - Beta
Classifier: Environment :: Console
Classifier: Intended Audience :: Science/Research
Classifier: License :: OSI Approved :: BSD License
Classifier: Operating System :: OS Independent
Classifier: Programming Language :: Python :: 3
Classifier: Topic :: Scientific/Engineering :: Chemistry
Classifier: Topic :: Scientific/Engineering :: Physics
Requires-Python: >=3.9
License-File: LICENSE.txt
Requires-Dist: bumps==1.0.3
Requires-Dist: matplotlib
Requires-Dist: numba
Requires-Dist: numpy
Requires-Dist: periodictable
Requires-Dist: scipy
Requires-Dist: orsopy
Provides-Extra: dev
Requires-Dist: ipython; extra == "dev"
Requires-Dist: matplotlib; extra == "dev"
Requires-Dist: nbsphinx; extra == "dev"
Requires-Dist: pre-commit; extra == "dev"
Requires-Dist: pydantic; extra == "dev"
Requires-Dist: pytest; extra == "dev"
Requires-Dist: pytest-cov; extra == "dev"
Requires-Dist: ruff; extra == "dev"
Requires-Dist: sphinx<8.2; extra == "dev"
Requires-Dist: versioningit; extra == "dev"
Provides-Extra: full
Requires-Dist: wxpython; extra == "full"
Requires-Dist: ipython; extra == "full"
Dynamic: license-file
